balm/__init__.py
balm/pp.py
balm/version.py
balm/data_processing/__init__.py
balm/data_processing/airr.py
balm/model/__init__.py
balm/model/balm.py
balm/model/tokenizer.py
balm_antibody-0.0.2.dist-info/LICENSE
balm_antibody-0.0.2.dist-info/METADATA
balm_antibody-0.0.2.dist-info/WHEEL
balm_antibody-0.0.2.dist-info/top_level.txt
balm_antibody-0.0.2.dist-info/RECORD
